osman/__init__.py
osman/config.py
osman/environment.py
osman/osman.py
osmanager-1.0.7.dist-info/LICENSE.md
osmanager-1.0.7.dist-info/METADATA
osmanager-1.0.7.dist-info/WHEEL
osmanager-1.0.7.dist-info/top_level.txt
osmanager-1.0.7.dist-info/RECORD
