Metadata-Version: 2.2
Name: osmanager
Version: 1.0.7
Summary: OpenSearch manager repository.
Home-page: https://github.com/strvcom/osman
Author: STRV DS Department <datascience.dept@strv.com>
Author-email: datascience.dept@strv.com
Requires-Python: >=3.10
License-File: LICENSE.md
Requires-Dist: pytest>=7.1
Requires-Dist: attrs>=22.1
Requires-Dist: certifi>=2022.9
Requires-Dist: charset-normalizer>=2.1
Requires-Dist: click>=8.1
Requires-Dist: idna>=3.4
Requires-Dist: iniconfig>=1.1
Requires-Dist: opensearch-py==2.6.0
Requires-Dist: packaging>=21.3
Requires-Dist: parameterized>=0.8.1
Requires-Dist: pluggy>=1.0
Requires-Dist: py>=1.11
Requires-Dist: pyparsing>=3.0
Requires-Dist: requests>=2.28
Requires-Dist: tomli>=2.0
Requires-Dist: urllib3>=1.26
Requires-Dist: requests-aws4auth>=1.1
Requires-Dist: deepdiff>=6.2
Dynamic: author
Dynamic: author-email
Dynamic: description
Dynamic: description-content-type
Dynamic: home-page
Dynamic: requires-dist
Dynamic: requires-python
Dynamic: summary
